pybtcc/__init__.py
pybtcc/_version.py
pybtcc/api.py
pybtcc/ratelimit.py
pybtcc-0.0.1a1.dist-info/DESCRIPTION.rst
pybtcc-0.0.1a1.dist-info/METADATA
pybtcc-0.0.1a1.dist-info/RECORD
pybtcc-0.0.1a1.dist-info/WHEEL
pybtcc-0.0.1a1.dist-info/metadata.json
pybtcc-0.0.1a1.dist-info/top_level.txt
